holymeow/__init__.py
holymeow/main.py
holymeow-0.6.0.dist-info/METADATA
holymeow-0.6.0.dist-info/WHEEL
holymeow-0.6.0.dist-info/entry_points.txt
holymeow-0.6.0.dist-info/RECORD
