Metadata-Version: 2.4
Name: holymeow
Version: 0.6.0
Summary: Add your description here
Author-email: pranav <pranavap96@gmail.com>
Requires-Python: >=3.13
